lyono/BUILD
lyono/__init__.py
lyono/abstract.py
lyono/clients/__init__.py
lyono/clients/http_client.py
lyono/common.py
lyono/formatting/BUILD
lyono/formatting/__init__.py
lyono/formatting/enums.py
lyono/formatting/models.py
lyono/typings.py
lyono-1.1.0.dist-info/WHEEL
lyono-1.1.0.dist-info/METADATA
lyono-1.1.0.dist-info/RECORD
