Metadata-Version: 2.1
Name: lyono
Version: 1.1.0
Summary: 
Author: Kevin Hill
Author-email: kah.kevin.hill@gmail.com
Requires-Python: >=3.9,<4.0
Classifier: Programming Language :: Python :: 3
Classifier: Programming Language :: Python :: 3.9
Requires-Dist: auto-all (>=1.3.0,<2.0.0)
Requires-Dist: datamodel-code-generator (>=0.6.10,<0.7.0)
Requires-Dist: genson (>=1.2.2,<2.0.0)
Requires-Dist: httpx (>=0.17.1,<0.18.0)
Requires-Dist: loguru (>=0.5.3,<0.6.0)
Requires-Dist: orjson (>=3.4.6,<4.0.0)
Requires-Dist: pydantic (>=1.7.3,<2.0.0)
